kegg2bipartitegraph/__init__.py
kegg2bipartitegraph/__main__.py
kegg2bipartitegraph/eggnog.py
kegg2bipartitegraph/esmecata.py
kegg2bipartitegraph/genbank.py
kegg2bipartitegraph/graph.py
kegg2bipartitegraph/kofamkoala.py
kegg2bipartitegraph/mapping.py
kegg2bipartitegraph/organism.py
kegg2bipartitegraph/picrust.py
kegg2bipartitegraph/reference.py
kegg2bipartitegraph/sbml.py
kegg2bipartitegraph/scope.py
kegg2bipartitegraph/seeds.py
kegg2bipartitegraph/utils.py
kegg2bipartitegraph/data/kegg_model/ec_to_gos.tsv
kegg2bipartitegraph/data/kegg_model/kegg_compound_name.tsv
kegg2bipartitegraph/data/kegg_model/kegg_hierarchy.json
kegg2bipartitegraph/data/kegg_model/kegg_mapping.tsv
kegg2bipartitegraph/data/kegg_model/kegg_metadata.json
kegg2bipartitegraph/data/kegg_model/kegg_model.graphml
kegg2bipartitegraph/data/kegg_model/kegg_model.sbml
kegg2bipartitegraph/data/kegg_model/kegg_modules.tsv
kegg2bipartitegraph/data/kegg_model/kegg_pathways.tsv
kegg2bipartitegraph/data/kegg_model/kegg_removed_changed_reaction.tsv
kegg2bipartitegraph/data/kegg_model/seed_hyperterm_med.sbml
kegg2bipartitegraph/data/kegg_model/seed_hyperterm_med.txt
kegg2bipartitegraph/data/kegg_model/seed_union_all.sbml
kegg2bipartitegraph/data/kegg_model/seed_union_all.txt
kegg2bipartitegraph/data/kegg_model/seeds_meso_medium.sbml
kegg2bipartitegraph/data/kegg_model/seeds_meso_medium.txt
kegg2bipartitegraph/data/kegg_model/seeds_psychromed.sbml
kegg2bipartitegraph/data/kegg_model/seeds_psychromed.txt
kegg2bipartitegraph/data/kegg_model/seeds_therm_med.sbml
kegg2bipartitegraph/data/kegg_model/seeds_therm_med.txt
kegg2bipartitegraph-0.2.3.dist-info/LICENSE
kegg2bipartitegraph-0.2.3.dist-info/METADATA
kegg2bipartitegraph-0.2.3.dist-info/WHEEL
kegg2bipartitegraph-0.2.3.dist-info/entry_points.txt
kegg2bipartitegraph-0.2.3.dist-info/top_level.txt
kegg2bipartitegraph-0.2.3.dist-info/RECORD
