Metadata-Version: 2.2
Name: kegg2bipartitegraph
Version: 0.2.3
Summary: Reconstruct metabolic bipartite graph using KEGG
Author: Arnaud Belcour
License: GPL-3.0-or-later
Project-URL: Homepage, https://github.com/ArnaudBelcour/kegg2bipartitegraph
Project-URL: Changelog, https://github.com/ArnaudBelcour/kegg2bipartitegraph/blob/main/CHANGELOG.md
License-File: LICENSE
Requires-Dist: bioservices
Requires-Dist: python-libsbml
Requires-Dist: networkx
